{"about_index.md":"DDwTMLSI","fzlc_index.md":"BLfFSYWg","sbzz_index.md":"BuBjQCWm","sbzr_index.md":"Cs30iKJJ","posts_releasesbjm.md":"BVuJhuHR","gdfw_index.md":"Bu4H3H6I","faq_index.md":"n1n_eG3v","vzpz_index.md":"Crq0jv71","sbjc_index.md":"BRBlSlEP","sbjm_index.md":"BBO9jLPl","posts_2023年6月22日声笔更新.md":"Bm2bvd2U","posts_howtodebuglibrimeonwindows.md":"DYFrSV9l","posts_addmodew.md":"By1JLODw","sbfx_index.md":"DFDyKFiO","sbjz_index.md":"wS682cYG","sbxh_index.md":"61ob6dDt","sbhz_index.md":"9Jfw6O1n","index.md":"DVKnlQ53","sbfd_index.md":"DH9gYEXQ","sbfm_index.md":"DBlvZbUh","sbpy_index.md":"AHwhq7J3","readme.md":"GMNhZoMd","posts_win32or64.md":"DbXdSgq1","posts_upgrade8-5.md":"CDy9IUty","posts_个体词汇与全体词汇关系猜想.md":"DyRopcHY","posts_中文盲打分级.md":"DBEoO0l6","posts_中文输入模式.md":"CG-YJEtz","posts_key-articles.md":"DZL0HvnS","posts_几个输入方案单字前1500数据对比.md":"ZXQegxnG","posts_sbxmtxxg.md":"D090zRZU","posts_输入法词库转换工具.md":"DzilX1m0","posts_声笔2023年8月18日更新纪要.md":"77sHq7yy","public_readme.md":"Bf463k6p","posts_声笔输入法9x的安装与配置.md":"CeVD-Ttn","posts_拼音输入宝典.md":"C999CFsm","posts_weasel4sbxlm-0-14-3-0.md":"CKjnLBz-","posts_解密打字速度.md":"Y-KRmrI8","posts_sbxlm9-0.md":"Dm0Lndbm","posts_输入对比之一.md":"Demlu8I_","posts_xlhyjbs.md":"BWHU-1JK","posts_hzsrcj.md":"Bk1hJBPs","posts_sbxlmrevamp.md":"Bu3YB7lT","posts_sbdp.md":"Dd7Gqht9","posts_sbjmzdsj.md":"DBYOw4aS","posts_cikuyh.md":"lnVgswPn","posts_编码中频率的作用.md":"YE6SymxI","posts_小狼毫的可视化配置工具.md":"nuGSnqYw","posts_disable-redirect.md":"BFq0c7lt","posts_srfgsm.md":"CmjgQ8u4","posts_blogpost20200808.md":"BLkYKRrq","posts_sentencemodes.md":"DXW13yo5","posts_update191108.md":"BlCMUEn0","posts_sbxlmxg.md":"KKZaDwwq","posts_sbspyh.md":"D2MphqLA","posts_声笔飞讯的个性化定制.md":"ByCE5_v-","posts_声笔飞系部首解释.md":"YjgONzj8","posts_如何根除流氓输入法.md":"BbPGF45l","posts_site-build.md":"CU2mN41l","posts_spfs.md":"DID3-6cc","posts_jmkzmsyh.md":"P45ZkQim","sbtf_index.md":"CdY_s3u-","posts_fmkmyh.md":"GE3d8vwo","posts_sbxlzj.md":"DgVI8nBG","posts_rime4sbxlm.md":"BzOsvhjB","posts_git-tips.md":"CpZ12wGt","posts_index.md":"BlmtQQHj","posts_main-imes.md":"ZclvB0T6","sbgj_index.md":"DwMSNfvL","posts_shared-dict.md":"BlCswLe5","posts_声笔码引起的反响摘录.md":"BN9utiqc","posts_pywtjj.md":"BJIr_UNl","posts_qzdzc.md":"Cey6sWv3","posts_hzbmsrfzs.md":"BQiMczoE","sbkd_index.md":"DncsV76n"}
