{"faq_index.md":"DSwxA2Wc","readme.md":"DpnzVmDv","sbjm_index.md":"DmRsXYZb","sbzr_index.md":"BaZfrQT8","sbfm_index.md":"gMSo-isU","sbfd_index.md":"C_8ESP9w","vzpz_index.md":"DCJXw57f","sbfx_index.md":"kL4EbA73","fzlc_index.md":"Cy6iefSX","posts_sbxlmrevamp.md":"DIxRx4yD","posts_releasesbjm.md":"CCv8CPG0","posts_cikuyh.md":"C_DUdiEU","posts_howtodebuglibrimeonwindows.md":"VUFsOQig","posts_git-tips.md":"BnfXbgxA","posts_rime4sbxlm.md":"BAtDDUgx","posts_hzbmsrfzs.md":"B5ZM3CEi","posts_qzdzc.md":"bPnH0p_V","posts_sbxlmxg.md":"C5J3gHoz","posts_fmkmyh.md":"Ch34F-yn","posts_update191108.md":"BuI1a0DY","posts_srfgsm.md":"uVrSKjpH","posts_upgrade8-5.md":"Ch3EvyIJ","posts_hzsrcj.md":"CbxAtlcB","posts_sbjmzdsj.md":"CVXTrGTU","posts_pywtjj.md":"CjJeDUS3","posts_blogpost20200808.md":"W-_tJkgL","posts_index.md":"DcbfSVRI","posts_jmkzmsyh.md":"CF_C4swM","posts_输入法词库转换工具.md":"PqwD7fhA","public_readme.md":"CeuAp4s9","posts_key-articles.md":"JTDRfyCU","gdfw_index.md":"Ch_2muDm","posts_main-imes.md":"RRojV518","posts_sbdp.md":"C7Fdr-Ko","posts_sbspyh.md":"BCuBQa4p","about_index.md":"fRO4TNr4","posts_shared-dict.md":"Bcl6oppv","posts_sbsp.md":"Dmra-YsG","posts_disable-redirect.md":"DkgOkdNL","posts_sbxlm9-0.md":"CgD2rNjg","index.md":"RZk-H7VA","posts_2023年6月22日声笔更新.md":"eqDwCBhI","sbjc_index.md":"QM97EU6W","posts_如何根除流氓输入法.md":"BHNiZYMf","posts_weasel4sbxlm-0-14-3-0.md":"DYDanUCf","posts_addmodew.md":"Ce43BBkD","posts_拼音输入宝典.md":"Cmgo7lhd","posts_sentencemodes.md":"CR6KhbyP","posts_解密打字速度.md":"CMQwkL20","posts_spfs.md":"EqcbUD7D","posts_sbxmtxxg.md":"DmkvCjOS","sbxh_index.md":"nkscFINM","posts_win32or64.md":"B9Fzwsaj","posts_几个输入方案单字前1500数据对比.md":"CDeJPToO","posts_编码中频率的作用.md":"CrW26q-D","posts_xlhyjbs.md":"CX1dzM0T","posts_声笔2023年8月18日更新纪要.md":"BfXcIwho","posts_输入对比之一.md":"DRxC6kFy","posts_sbxlzj.md":"h-W-svgj","posts_个体词汇与全体词汇关系猜想.md":"BpBeVHfd","posts_中文盲打分级.md":"B-CaPJ6F","posts_声笔码引起的反响摘录.md":"CSpqgDd0","posts_声笔输入法9x的安装与配置.md":"C4YHv64u","posts_中文输入模式.md":"huS9_zVC","posts_site-build.md":"DGKy8pKU","posts_声笔飞系部首解释.md":"2zEUcUQn","posts_小狼毫的可视化配置工具.md":"DN6low4D","posts_声笔飞讯的个性化定制.md":"AjtlOvc_","sbgj_index.md":"Bo6ltITT","sbkd_index.md":"DChlbXRp","sbpy_index.md":"DwKk3rzu","sbtf_index.md":"FMr2_kLs"}
