{"sbf_index.md":"CX49aSH3","readme.md":"CPFbS6Ua","faq_index.md":"DgxxnutW","sbjm_index.md":"D9CW9kGd","gdfw_index.md":"WNV_niv4","posts_sbxlmrevamp.md":"D5h94fkt","fzlc_index.md":"48kzs3d5","sbxh_index.md":"B6znIKUR","posts_releasesbjm.md":"BblomqO0","posts_声笔码引起的反响摘录.md":"CvBTNHXv","sbj_index.md":"BdIuGWVK","posts_声笔输入法9x的安装与配置.md":"I1-uEHTE","sbs_index.md":"DFM53u7V","posts_main-imes.md":"DroOZBXH","sbzz_index.md":"DT8cpANv","posts_pywtjj.md":"BCzoK-b-","vzpz_index.md":"D-WurSon","posts_qzdzc.md":"BEFAdpqW","index.md":"bP80l40b","posts_addmodew.md":"B4gxrBus","sbfm_index.md":"BvVitCvM","sbjf_index.md":"BRJgVv-k","posts_rime4sbxlm.md":"BLWpEpNa","sbjp_index.md":"De9dBqWQ","posts_jmkzmsyh.md":"KRUtw8-3","posts_sbdp.md":"nC3ZIZOD","posts_sbspyh.md":"AxvVs4Lg","sbjc_index.md":"FFkNj74j","posts_sbjmzdsj.md":"BIDlhMTp","posts_shared-dict.md":"r27U0VSA","posts_site-build.md":"C5rYO6KX","posts_spfs.md":"B6kAKXlg","posts_srfgsm.md":"WhhwM9y0","posts_upgrade8-5.md":"BuUStzvb","posts_weasel4sbxlm-0-14-3-0.md":"C5px9Mq2","posts_xlhyjbs.md":"C6RfiiE-","posts_update191108.md":"CS8jUMYW","posts_win32or64.md":"CTBQ-67T","posts_个体词汇与全体词汇关系猜想.md":"B3lQCD0D","posts_中文盲打分级.md":"Ds898MWN","posts_中文输入模式.md":"RLf-sjZ2","sbzr_index.md":"BjIM4igg","posts_冰雪四拼.md":"B9ogp0VH","posts_disable-redirect.md":"Dp5LJxyQ","about_index.md":"CBTod4hC","posts_声笔飞讯的个性化定制.md":"6LYZF-L6","posts_blogpost20200808.md":"DUaH_b1T","posts_howtodebuglibrimeonwindows.md":"DBrAclID","sbfx_index.md":"C2F0aNe5","posts_如何根除流氓输入法.md":"DRKgXW0d","posts_小狼毫的可视化配置工具.md":"CUp0yth0","posts_sentencemodes.md":"Cz_wi5w3","posts_2023年6月22日声笔更新.md":"BkqhuUD_","posts_编码中频率的作用.md":"4JCLk6Is","posts_解密打字速度.md":"BqktY7mh","posts_拼音输入宝典.md":"NtIJ0pG7","sbfd_index.md":"BgGs-Vv2","public_readme.md":"gib9xj3-","sbtf_index.md":"YRmu2C72","posts_输入对比之一.md":"CKhYpqDX","posts_输入法词库转换工具.md":"YalmdL9T","posts_key-articles.md":"CCcZeO5h","posts_sbxlm9-0.md":"CGCFB6Te","posts_声笔2023年8月18日更新纪要.md":"Dqxt3yQh","posts_sbxlmxg.md":"BetrUUug","posts_git-tips.md":"BdRJkNd_","posts_sbxlzj.md":"D1B8M1bi","sbgj_index.md":"D3rHFFP8","posts_hzbmsrfzs.md":"BhHPMeHh","sbhz_index.md":"D4B0GsBv","posts_hzsrcj.md":"nAKvAU4D","posts_sbxmtxxg.md":"eGz8482V","posts_cikuyh.md":"BYL5H2vU","posts_几个输入方案单字前1500数据对比.md":"BWzQhXkG","sbpy_index.md":"CAhv_eCu","posts_声笔飞系部首解释.md":"lE8RGs07","posts_fmkmyh.md":"Rob9WqVc","posts_index.md":"IdIuBr1I","sbkd_index.md":"Bbh4vmLI"}
