{"about_index.md":"CbYpp6R2","sbfm_index.md":"CPkJb61G","gdfw_index.md":"CIJ_ZEX1","faq_index.md":"BTu1iaIc","readme.md":"Bxe1ZgjQ","sbfx_index.md":"CupIaVmp","sbj_index.md":"CKCRobHo","sbfd_index.md":"D--ei46w","sbf_index.md":"DyorpEHn","fzlc_index.md":"C3EBVnfO","posts_sentencemodes.md":"CFcLUCFw","posts_2023年6月22日声笔更新.md":"D6QKi9x-","posts_addmodew.md":"CV5L514D","posts_howtodebuglibrimeonwindows.md":"ClvjBEgx","posts_releasesbjm.md":"CGw35UHs","posts_rime用户数据同步方法.md":"DA737wJS","posts_sbxlmrevamp.md":"HbEc2PHE","sbhz_index.md":"Df5R6xaA","index.md":"F-IzK_9R","posts_blogpost20200808.md":"DtGJ_FTF","posts_disable-redirect.md":"qf_6qNpw","posts_git-tips.md":"CayBLYCi","sbsp_index.md":"6T2HphAh","posts_中文盲打分级.md":"CRQfmL9T","posts_pywtjj.md":"IuYN0Mhn","sbjm_index.md":"mVmrnxIy","sbjp_index.md":"Cx9RKgoS","sbpy_index.md":"BfiWK48Z","posts_cikuyh.md":"DTl1RoTh","sbxh_index.md":"CzCR4uGK","posts_声笔sql脚本整理.md":"OTEPa3xv","posts_声笔2023年8月18日更新纪要.md":"BAPqqcuR","posts_weasel4sbxlm-0-14-3-0.md":"CQI3Yz_0","posts_rime4sbxlm.md":"BojAawYw","posts_sbdp.md":"z4XtTfnk","posts_upgrade8-5.md":"CmISBPzj","posts_几个输入方案单字前1500数据对比.md":"CiZWuoaU","posts_声笔飞讯竞速怎么设置好.md":"E5TDMmmQ","vzpz_index.md":"Bx-4i1qA","posts_如何根除流氓输入法.md":"LG2ZGjIB","posts_小狼毫的可视化配置工具.md":"C0aXW-op","posts_qzdzc.md":"BfmHDrkl","posts_拼音输入宝典.md":"KqqZtsCr","sbjc_index.md":"dj4_UmbZ","sbzr_index.md":"Dykxf-LZ","posts_update191108.md":"D_cMOYCw","posts_srfgsm.md":"C_PCp6ks","posts_site-build.md":"yjbUEznZ","posts_个体词汇与全体词汇关系猜想.md":"W6Q-g_1D","posts_编码中频率的作用.md":"DefObT-W","posts_index.md":"C-6fZF7u","posts_sbspyh.md":"CBQ56X6o","posts_win32or64.md":"BS32R0CS","posts_xlhyjbs.md":"xUJdv3p7","sbzz_index.md":"B4-B0g6f","posts_jmkzmsyh.md":"BjSqYv6x","posts_fmkmyh.md":"DJksLQqV","public_readme.md":"BOENPfYK","posts_声笔飞讯的个性化定制.md":"B_XV1SLF","posts_声笔飞系部首解释.md":"BrA-x1Ai","posts_输入对比之一.md":"CiFf4E4F","posts_解密打字速度.md":"CuvMQDV_","posts_sbjmzdsj.md":"Cm5PiCHu","posts_如何在deepin上安装声笔输入法.md":"-pVnyUkK","posts_输入法词库转换工具.md":"CasKPK61","posts_sbxlm9-0.md":"QcAweqtX","posts_sbxlmxg.md":"CdwszlJ7","posts_sbxlzj.md":"DcjWBW5G","posts_sbxmtxxg.md":"DDtJCi_4","posts_shared-dict.md":"CQC551pe","sbgj_index.md":"BfTnsl8X","posts_spfs.md":"C4o7q6JE","posts_main-imes.md":"G5uNPfZT","posts_hzbmsrfzs.md":"aB9kKXRu","sbs_index.md":"DRZqBipB","posts_key-articles.md":"Ba4_eTRL","sbtf_index.md":"CI36yfJ9","posts_hzsrcj.md":"BYej8zdj","posts_声笔码引起的反响摘录.md":"FogJBiof","posts_声笔输入法9x的安装与配置.md":"Bbv_FFrK","posts_中文输入模式.md":"BEh91UmC","sbkd_index.md":"Do8LLDdM"}
